unphishable.py
unphishable-7.0.2.dist-info/licenses/LICENSE
unphishable-7.0.2.dist-info/METADATA
unphishable-7.0.2.dist-info/WHEEL
unphishable-7.0.2.dist-info/entry_points.txt
unphishable-7.0.2.dist-info/top_level.txt
unphishable-7.0.2.dist-info/RECORD
