Metadata-Version: 2.4
Name: unphishable
Version: 7.0.2
Summary: Advanced phishing detection CLI tool with multi-layer analysis
Author: Newton Achonduh
Author-email: UNPHISHABLE Security <security@unphishable.dev>
License: MIT
Project-URL: Homepage, https://github.com/unphishable/unphishable
Project-URL: Documentation, https://github.com/unphishable/unphishable#readme
Project-URL: Repository, https://github.com/unphishable/unphishable
Project-URL: Issues, https://github.com/unphishable/unphishable/issues
Keywords: security,phishing,detection,cli,scanner,cybersecurity
Classifier: Programming Language :: Python :: 3
Classifier: License :: OSI Approved :: MIT License
Classifier: Operating System :: OS Independent
Classifier: Topic :: Security
Classifier: Topic :: Internet
Classifier: Development Status :: 4 - Beta
Classifier: Intended Audience :: End Users/Desktop
Classifier: Intended Audience :: System Administrators
Classifier: Environment :: Console
Classifier: Natural Language :: English
License-File: LICENSE
Dynamic: author
Dynamic: license-file
